spacy_setfit/__init__.py
spacy_setfit/models.py
spacy_setfit/schemas.py
spacy_setfit-0.1.5.dist-info/LICENSE
spacy_setfit-0.1.5.dist-info/METADATA
spacy_setfit-0.1.5.dist-info/WHEEL
spacy_setfit-0.1.5.dist-info/entry_points.txt
spacy_setfit-0.1.5.dist-info/RECORD
