Metadata-Version: 2.1
Name: spacy-setfit
Version: 0.1.5
Summary: 
Author: davidberenstein1957
Author-email: david.m.berenstein@gmail.com
Requires-Python: >=3.8,<4.0
Classifier: Programming Language :: Python :: 3
Classifier: Programming Language :: Python :: 3.8
Classifier: Programming Language :: Python :: 3.9
Classifier: Programming Language :: Python :: 3.10
Classifier: Programming Language :: Python :: 3.11
Requires-Dist: rich (>=13,<14)
Requires-Dist: setfit (>=0.7,<0.8)
Requires-Dist: spacy (>=3,<4)
